pyreview/__init__.py
pyreview/__main__.py
pyreview/create_review_app.py
pyreview/pipeline.py
pyreview/source_blob.py
pyreview/utils.py
pyreview-1.2.0.dist-info/LICENSE
pyreview-1.2.0.dist-info/METADATA
pyreview-1.2.0.dist-info/WHEEL
pyreview-1.2.0.dist-info/entry_points.txt
pyreview-1.2.0.dist-info/top_level.txt
pyreview-1.2.0.dist-info/RECORD
