Metadata-Version: 2.1
Name: pyreview
Version: 1.2.0
Summary: Deploy tool for Heroku Review App using Bitbucket Pipelines.
Home-page: https://github.com/franciscoafonsoo/pyreview
Author: Francisco Pires
Author-email: f.pires.dev@icloud.com
License: gpl-3.0
Platform: UNKNOWN
Classifier: Programming Language :: Python :: 3
Classifier: Programming Language :: Python :: 3 :: Only
Classifier: Programming Language :: Python :: 3.6
Classifier: Programming Language :: Python :: 3.7
Classifier: Programming Language :: Python :: 3.8
Classifier: Programming Language :: Python :: Implementation :: CPython
Classifier: Programming Language :: Python :: Implementation :: PyPy
Requires-Python: >=3.6.1
Requires-Dist: requests (==2.25.1)
Requires-Dist: python-dotenv (==0.15.0)
